hidden_memo/__init__.py
hidden_memo/main.py
hidden_memo/py.typed
hidden_memo-0.1.0.dist-info/METADATA
hidden_memo-0.1.0.dist-info/WHEEL
hidden_memo-0.1.0.dist-info/entry_points.txt
hidden_memo-0.1.0.dist-info/RECORD
