Metadata-Version: 2.4
Name: hidden-memo
Version: 0.1.0
Summary: A hidden NoSQL MCP server for unstructured data.
Author-email: choi_hyk <blindlchoil@gmail.com>
Requires-Python: >=3.11
Requires-Dist: mcp>=1.0.0
Requires-Dist: tinydb>=4.8.0
Requires-Dist: typer>=0.21.1
